pydantic_serdes/__init__.py
pydantic_serdes/config.py
pydantic_serdes/custom_collections.py
pydantic_serdes/datastore.py
pydantic_serdes/decorators.py
pydantic_serdes/dumpers.py
pydantic_serdes/exceptions.py
pydantic_serdes/loaders.py
pydantic_serdes/models.py
pydantic_serdes/utils.py
pydantic_serdes-1.0.4.dist-info/LICENSE
pydantic_serdes-1.0.4.dist-info/METADATA
pydantic_serdes-1.0.4.dist-info/WHEEL
pydantic_serdes-1.0.4.dist-info/RECORD
