Metadata-Version: 2.1
Name: pydantic_serdes
Version: 1.0.4
Summary: A Python package that standardizes data serialization and deserialization from/to pydantic models.
License: MIT
Keywords: serialization,deserialization,parsing,pydantic-models,serialized-to-pydantic,pydantic-to-serialized
Author: André Lima
Requires-Python: >=3.8,<4.0
Classifier: License :: OSI Approved :: MIT License
Classifier: Programming Language :: Python :: 3
Classifier: Programming Language :: Python :: 3.8
Classifier: Programming Language :: Python :: 3.9
Classifier: Programming Language :: Python :: 3.10
Classifier: Programming Language :: Python :: 3.11
Classifier: Programming Language :: Python :: 3.12
Requires-Dist: email-validator (>=2.1.0.post1,<3.0.0)
Requires-Dist: jinja2 (>=3.1.3,<4.0.0)
Requires-Dist: pydantic (>=2.6.1,<3.0.0)
Requires-Dist: pyyaml (>=6.0.1,<7.0.0)
Requires-Dist: sortedcontainers (>=2.4.0,<3.0.0)
Requires-Dist: toml (>=0.10.2,<0.11.0)
Project-URL: Documentation, https://github.com/theandrelima/pydantic-serdes
